README.txt
setup.py
docs/HISTORY.txt
docs/INSTALL.txt
docs/LICENSE.GPL
docs/LICENSE.txt
plone/__init__.py
plone.recipe.deliverance.egg-info/PKG-INFO
plone.recipe.deliverance.egg-info/SOURCES.txt
plone.recipe.deliverance.egg-info/dependency_links.txt
plone.recipe.deliverance.egg-info/entry_points.txt
plone.recipe.deliverance.egg-info/namespace_packages.txt
plone.recipe.deliverance.egg-info/paster_plugins.txt
plone.recipe.deliverance.egg-info/requires.txt
plone.recipe.deliverance.egg-info/top_level.txt
plone.recipe.deliverance.egg-info/zip-safe
plone/recipe/__init__.py
plone/recipe/deliverance/__init__.py
plone/recipe/deliverance/ctl.py
plone/recipe/deliverance/recipe.py
plone/recipe/deliverance/templates.py
