Metadata-Version: 1.0
Name: plone.recipe.deliverance
Version: 1.0b3
Summary: Install Deliverance
Home-page: http://svn.plone.org/svn/collective/buildout/plone.recipe.deliverance
Author: Martin Aspeli
Author-email: optilude@gmx.net
License: ZPL 2.1
Platform: UNKNOWN
Classifier: License :: OSI Approved :: Zope Public License
Classifier: Framework :: Buildout
Classifier: Framework :: Plone
Classifier: Framework :: Zope2
Classifier: Programming Language :: Python
